{
  "data": {
    "md5": "f8a70ad6f315712159406c5150d92f0c",
    "path": "asset/ui/MainWait.layout",
    "root": {
      "anchor": {
        "HorizontalAlignment": "Centre",
        "VerticalAlignment": "Centre"
      },
      "children": [
        {
          "__OBJ_TYPE": "DefaultWindow",
          "Alpha": 0.985,
          "anchor": {
            "VerticalAlignment": "Centre"
          },
          "children": [
            {
              "__OBJ_TYPE": "VerticalLayoutContainer",
              "anchor": {
                "HorizontalAlignment": "Centre",
                "VerticalAlignment": "Centre"
              },
              "children": [
                {
                  "__OBJ_TYPE": "DefaultWindow",
                  "children": [
                    {
                      "__OBJ_TYPE": "StaticImage",
                      "anchor": {
                        "HorizontalAlignment": "Centre",
                        "VerticalAlignment": "Bottom"
                      },
                      "id": {
                        "value": "29efa110-8671-440c-b484-49a9bb91363b"
                      },
                      "Image": {
                        "asset": "asset/ui/MainPlay/candy.png"
                      },
                      "size": {
                        "UDim_X": {
                          "Offect": 50
                        },
                        "UDim_Y": {
                          "Offect": 50
                        }
                      }
                    },
                    {
                      "__OBJ_TYPE": "StaticText",
                      "anchor": {
                        "HorizontalAlignment": "Centre"
                      },
                      "Font": "Fonts/shloprg",
                      "Font_size": 20,
                      "HorzFormatting": "CentreAligned",
                      "id": {
                        "value": "514e7b53-f6fc-4b39-bd59-892a4fbac34e"
                      },
                      "name": "count",
                      "size": {
                        "UDim_X": {
                          "Offect": 100
                        },
                        "UDim_Y": {
                          "Offect": 50
                        }
                      },
                      "Text": "0",
                      "text_key": {
                        "value": "asset/ui/MainWait.layout.StaticText#1e67209d-4b97-4982-a7ba-bcc1ccc4ee1f"
                      },
                      "TextColours": {
                        "b": 255,
                        "g": 255,
                        "r": 255
                      },
                      "VertFormatting": "BottomAligned"
                    }
                  ],
                  "id": {
                    "value": "9febe643-6c63-4692-93a7-313bec87e11e"
                  },
                  "name": "candyWin",
                  "size": {
                    "UDim_X": {
                      "Offect": 100
                    },
                    "UDim_Y": {
                      "Offect": 100
                    }
                  }
                },
                {
                  "__OBJ_TYPE": "DefaultWindow",
                  "children": [
                    {
                      "__OBJ_TYPE": "Button",
                      "HoverImage": {
                        "asset": "asset/ui/MainWait/CameraEye.png"
                      },
                      "id": {
                        "value": "8402fb3b-ab2c-4a99-bed0-41eb988f7747"
                      },
                      "NormalImage": {
                        "asset": "asset/ui/MainWait/CameraEye.png"
                      },
                      "PushedImage": {
                        "asset": "asset/ui/MainWait/CameraEye.png"
                      },
                      "size": {
                        "UDim_X": {
                          "Offect": 100
                        },
                        "UDim_Y": {
                          "Offect": 100
                        }
                      },
                      "Text": "",
                      "text_key": {
                        "value": "asset/ui/MainWait.layout.Button#035874bb-a194-4bad-af97-06aac237883c"
                      }
                    },
                    {
                      "__OBJ_TYPE": "StaticText",
                      "Alpha": 0.994,
                      "anchor": {
                        "HorizontalAlignment": "Centre",
                        "VerticalAlignment": "Bottom"
                      },
                      "BorderWidth": 2,
                      "Font": "Fonts/CakeZombie",
                      "HorzFormatting": "CentreAligned",
                      "id": {
                        "value": "02b85f38-cdf4-4272-a9a8-df1fa5096381"
                      },
                      "size": {
                        "UDim_X": {
                          "Offect": 100
                        },
                        "UDim_Y": {
                          "Offect": 20
                        }
                      },
                      "Text": "Watch Mode",
                      "text_key": {
                        "value": "asset/ui/MainWait.layout.StaticText#046c19d7-565d-4e60-86b0-4caae8e6b6d0"
                      },
                      "VertFormatting": "CentreAligned"
                    }
                  ],
                  "id": {
                    "value": "3ee93c3a-b8b3-4ccf-8245-e2fc9f14ee12"
                  },
                  "name": "watchMode",
                  "pos": {
                    "UDim_Y": {
                      "Offect": 100
                    }
                  },
                  "size": {
                    "UDim_X": {
                      "Offect": 100
                    },
                    "UDim_Y": {
                      "Offect": 120
                    }
                  }
                }
              ],
              "id": {
                "value": "4df73f62-2cb8-48a9-843a-b4290e0691e1"
              },
              "name": "ListBtn",
              "size": {
                "UDim_Y": {
                  "Offect": 220
                }
              },
              "WindowTouchThroughMode": "MousePassThroughOpen"
            }
          ],
          "id": {
            "value": "4071116b-2168-45e5-a5c4-a76c7f7012ec"
          },
          "name": "Menu",
          "size": {
            "UDim_X": {
              "Offect": 200
            }
          },
          "WindowTouchThroughMode": "MousePassThroughOpen"
        }
      ],
      "id": {
        "value": "b98e2244-ad03-4ccc-8422-c1481c1af941"
      },
      "size": {
        "UDim_X": {
          "Offect": 0,
          "Scale": 1
        },
        "UDim_Y": {
          "Offect": 0,
          "Scale": 1
        }
      },
      "WindowTouchThroughMode": "MousePassThroughOpen"
    }
  },
  "meta": {
    "EXPORT": {
      "layout": "f8a70ad6f315712159406c5150d92f0c",
      "triggers.bts": "d1fd7037f4941cd1b8cbfb94bb926990"
    },
    "VERSION": "0.24"
  }
}